Workbook
Name feriados: [1]Feriados!$A$2:$A$1265

Sheet ts
A1: bond_id | B1: issuer | C1: maturity | D1: bond_type | E1: exchange id | F1: sector | G1: obs_date | H1: month | I1: spread | J1: vix | K1: fed_funds_rate | N1: usd_brl | O1: gdp_yoy | P1: debt_gdp | Q1: cf_cash_oper_to_tot_asset | R1: amount_issued_to_bs_tot_asset | S1: tot_debt_to_ebitda | T1: days_to_maturity | U1: synthetic_cds_brl
A2: AM250786 Corp | B2: MRV ENGENHARIA PARTICIP | C2: 2/15/2022 | D2: BRAZIL IPCA+SPREAD | E2: MRVE3 BZ | F2: Home Builders | G2: 42916 | H2: 42916 | I2: 2.4668 | J2: 11.18 | K2: 1.04 | L2: =DATE(YEAR(G2),MONTH(G2),DAY(G2)) -> 42916 | M2: =VLOOKUP(L2,Sheet1!$B$5:$C$4117,2,0) -> 1.163 | N2: 3.3082 | O2: 0.79 | P2: -9.45 | Q2: 2.0910397 | R2: 6.0559379 | S2: 19.296258 | T2: 4.6150794 | U2: 3.8953252
A3: AM250786 Corp | B3: MRV ENGENHARIA PARTICIP | C3: 2/15/2022 | D3: BRAZIL IPCA+SPREAD | E3: MRVE3 BZ | F3: Home Builders | G3: 42947 | H3: 42947 | I3: 2.2299999 | J3: 10.26 | K3: 1.15 | L3: =DATE(YEAR(G3),MONTH(G3),DAY(G3)) -> 42947 | M3: =VLOOKUP(L3,Sheet1!$B$5:$C$4117,2,0) -> 1.161 | N3: 3.1254 | O3: 0.79 | P3: -9.45 | Q3: 6.6499526 | R3: 5.6131362 | S3: 15.349094 | T3: 4.531746 | U3: 3.9363574
A4: AM250786 Corp | B4: MRV ENGENHARIA PARTICIP | C4: 2/15/2022 | D4: BRAZIL IPCA+SPREAD | E4: MRVE3 BZ | F4: Home Builders | G4: 42978 | H4: 42978 | I4: 3.0029999 | J4: 10.59 | K4: 1.16 | L4: =DATE(YEAR(G4),MONTH(G4),DAY(G4)) -> 42978 | M4: =VLOOKUP(L4,Sheet1!$B$5:$C$4117,2,0) -> 1.1585 | N4: 3.1491 | O4: 0.79 | P4: -9.45 | Q4: 6.6499526 | R4: 5.6131362 | S4: 15.349094 | T4: 4.4404762 | U4: 3.9777411
A5: AM250786 Corp | B5: MRV ENGENHARIA PARTICIP | C5: 2/15/2022 | D5: BRAZIL IPCA+SPREAD | E5: MRVE3 BZ | F5: Home Builders | G5: 43007 | H5: 43008 | I5: 2.7870001 | J5: 9.51 | K5: 1.15 | L5: =DATE(YEAR(G5),MONTH(G5),DAY(G5)) -> 43007 | M5: =VLOOKUP(L5,Sheet1!$B$5:$C$4117,2,0) -> 1.193 | N5: 3.1625 | O5: 1.64 | P5: -8.73 | Q5: 6.6499526 | R5: 5.6131362 | S5: 15.349094 | T5: 4.3611111 | U5: 4.010667
A6: AM250786 Corp | B6: MRV ENGENHARIA PARTICIP | C6: 2/15/2022 | D6: BRAZIL IPCA+SPREAD | E6: MRVE3 BZ | F6: Home Builders | G6: 43039 | H6: 43039 | I6: 3.3816999 | J6: 10.18 | K6: 1.15 | L6: =DATE(YEAR(G6),MONTH(G6),DAY(G6)) -> 43039 | M6: =VLOOKUP(L6,Sheet1!$B$5:$C$4117,2,0) -> 1.273 | N6: 3.2713 | O6: 1.64 | P6: -8.73 | Q6: 6.7083834 | R6: 5.4950716 | S6: 14.055061 | T6: 4.2777778 | U6: 4.0421374
A7: AM250786 Corp | B7: MRV ENGENHARIA PARTICIP | C7: 2/15/2022 | D7: BRAZIL IPCA+SPREAD | E7: MRVE3 BZ | F7: Home Builders | G7: 43069 | H7: 43069 | I7: 3.7126999 | J7: 11.28 | K7: 1.16 | L7: =DATE(YEAR(G7),MONTH(G7),DAY(G7)) -> 43069 | M7: =VLOOKUP(L7,Sheet1!$B$5:$C$4117,2,0) -> 1.37226 | N7: 3.2681 | O7: 1.64 | P7: -8.73 | Q7: 6.7083834 | R7: 5.4950716 | S7: 14.055061 | T7: 4.1984127 | U7: 4.0691199
A8: AM250786 Corp | B8: MRV ENGENHARIA PARTICIP | C8: 2/15/2022 | D8: BRAZIL IPCA+SPREAD | E8: MRVE3 BZ | F8: Home Builders | G8: 43098 | H8: 43100 | I8: 3.4667999 | J8: 11.04 | K8: 1.3 | L8: =DATE(YEAR(G8),MONTH(G8),DAY(G8)) -> 43098 | M8: =VLOOKUP(L8,Sheet1!$B$5:$C$4117,2,0) -> 1.431 | N8: 3.3125 | O8: 2.58 | P8: -7.77 | Q8: 6.7083834 | R8: 5.4950716 | S8: 14.055061 | T8: 4.1190476 | U8: 4.0931516
A9: AM250786 Corp | B9: MRV ENGENHARIA PARTICIP | C9: 2/15/2022 | D9: BRAZIL IPCA+SPREAD | E9: MRVE3 BZ | F9: Home Builders | G9: 43131 | H9: 43131 | I9: 3.5194999 | J9: 13.54 | K9: 1.41 | L9: =DATE(YEAR(G9),MONTH(G9),DAY(G9)) -> 43131 | M9: =VLOOKUP(L9,Sheet1!$B$5:$C$4117,2,0) -> 1.5255 | N9: 3.1875 | O9: 2.58 | P9: -7.77 | Q9: 5.4878378 | R9: 5.5563898 | S9: 17.764548 | T9: 4.031746 | U9: 4.1161373
A10: AM250786 Corp | B10: MRV ENGENHARIA PARTICIP | C10: 2/15/2022 | D10: BRAZIL IPCA+SPREAD | E10: MRVE3 BZ | F10: Home Builders | G10: 43159 | H10: 43159 | I10: 3.5223998 | J10: 19.85 | K10: 1.42 | L10: =DATE(YEAR(G10),MONTH(G10),DAY(G10)) -> 43159 | M10: =VLOOKUP(L10,Sheet1!$B$5:$C$4117,2,0) -> 1.613 | N10: 3.2475 | O10: 2.58 | P10: -7.77 | Q10: 5.4878378 | R10: 5.5563898 | S10: 17.764548 | T10: 3.9603175 | U10: 4.1322249
A11: AM250786 Corp | B11: MRV ENGENHARIA PARTICIP | C11: 2/15/2022 | D11: BRAZIL IPCA+SPREAD | E11: MRVE3 BZ | F11: Home Builders | G11: 43189 | H11: 43190 | I11: 3.4460002 | J11: 19.97 | K11: 1.51 | L11: =DATE(YEAR(G11),MONTH(G11),DAY(G11)) -> 43189 | M11: =VLOOKUP(L11,Sheet1!$B$5:$C$4117,2,0) -> 1.723 | N11: 3.3063 | O11: 1.9 | P11: -7.3 | Q11: 5.4878378 | R11: 5.5563898 | S11: 17.764548 | T11: 3.8730159 | U11: 4.1485247
A12: AM250786 Corp | B12: MRV ENGENHARIA PARTICIP | C12: 2/15/2022 | D12: BRAZIL IPCA+SPREAD | E12: MRVE3 BZ | F12: Home Builders | G12: 43220 | H12: 43220 | I12: 3.3745002 | J12: 15.93 | K12: 1.69 | L12: =DATE(YEAR(G12),MONTH(G12),DAY(G12)) -> 43220 | M12: =VLOOKUP(L12,Sheet1!$B$5:$C$4117,2,0) -> 1.833 | N12: 3.5063 | O12: 1.9 | P12: -7.3 | Q12: 11.697276 | R12: 5.6549899 | S12: 15.823253 | T12: 3.7936508 | U12: 4.1600957
A13: AM250786 Corp | B13: MRV ENGENHARIA PARTICIP | C13: 2/15/2022 | D13: BRAZIL IPCA+SPREAD | E13: MRVE3 BZ | F13: Home Builders | G13: 43251 | H13: 43251 | I13: 3.1892001 | J13: 15.43 | K13: 1.7 | L13: =DATE(YEAR(G13),MONTH(G13),DAY(G13)) -> 43251 | M13: =VLOOKUP(L13,Sheet1!$B$5:$C$4117,2,0) -> 1.886 | N13: 3.7239 | O13: 1.9 | P13: -7.3 | Q13: 11.697276 | R13: 5.6549899 | S13: 15.823253 | T13: 3.7063492 | U13: 4.1692082
... A4230: ZQ942599 Corp | B4230: CONTEINERES VILA CONDE | C4230: 11/15/2031 | D4230: BRAZIL IPCA+SPREAD | E4230: STBP3 BZ | F4230: Transportation | G4230: 45838 | H4230: 45838 | I4230: 0.82199981 | J4230: 16.73 | K4230: 4.33 | L4230: =DATE(YEAR(G4230),MONTH(G4230),DAY(G4230)) -> 45838 | M4230: =VLOOKUP(L4230,Sheet1!$B$5:$C$4117,2,0) -> 4.28217 | N4230: 5.4316 | O4230: 2.85 | P4230: -7.3 | Q4230: 71.93088 | R4230: 10.870509 | S4230: 9.3537415 | T4230: 6.3531746 | U4230: 2.3960225

Sheet Sheet1
A1: start | B1: 40179
B2: =TODAY() -> 45988
A5: USSOC BGN Curncy | B5: {=_xll.BDH(A5,"px last",B1,B2)} -> 40179 | C5: 0.162
B6: 40182 | C6: 0.162
B7: 40183 | C7: 0.155
B8: 40184 | C8: 0.146
B9: 40185 | C9: 0.145
B10: 40186 | C10: 0.143
B11: 40189 | C11: 0.143
B12: 40190 | C12: 0.1415
B13: 40191 | C13: 0.147
B14: 40192 | C14: 0.143
B15: 40193 | C15: 0.138
B16: 40196 | C16: 0.141 | D16: ``
B17: 40197 | C17: 0.1415
B18: 40198 | C18: 0.141
B19: 40199 | C19: 0.143
B20: 40200 | C20: 0.145
B21: 40203 | C21: 0.147
B22: 40204 | C22: 0.144
B23: 40205 | C23: 0.14725
B24: 40206 | C24: 0.15
B25: 40207 | C25: 0.144
B26: 40210 | C26: 0.145
B27: 40211 | C27: 0.149
B28: 40212 | C28: 0.153
... B4118: 45988 | C4118: 3.683

Sheet glossary
A1: Name | B1: .docx | C1: Source | D1: mnemonic / flds | E1: long name | F1: Comment | G1: Por que de la elección de las variables explicativas | H1: Cual es la relacción teorica de cada variable explicativa con la explicada y el signo esperable en el modelo de panel
A2: bond_id
A3: issuer
A4: maturity
A5: bond_type | E5: Explanatory variable: características del bono: tipo de instrumento
A6: exchange id
A7: sector | D7: SECTOR | E7: Explanatory variable: características de la empresa: sector económico
A8: obs_date
A9: month
A10: spread | B10: Spread de deuda corporativa en reales (por emisión o promedio ponderado). | C10: Calculated | E10: Dependent variable: Corporate bond spread in Brazilian reais
A11: vix | B11: Índice VIX (aversión global al riesgo) | C11: Bloomberg | D11: VIX Index | E11: Explanatory variable: Global volatility / risk aversion (VIX index)
A12: fed_funds_rate | B12: Tasas de interés internacionales (e.g. Fed Funds Rate) | C12: Bloomberg | D12: USSOC BGN Curncy | E12: Explanatory variable: International interest rates (e.g., Fed Funds Rate / US Federal Funds Effective Rate (continuous series) ) / Tasas de interés internacionales (e.g. Fed Funds Rate) Un Overnight Indexed Swap (OIS) es un swap de tipos de interés donde una parte paga una tasa fija y la otra una tasa flotante basada en la tasa overnight oficial (en EE. UU., el Effective Federal Funds Rate). La tasa fija del OIS a 3 meses (USSOC) refleja la expectativa del mercado sobre el promedio del tipo overnight durante ese período, por lo que funciona como una medida limpia y directa del “Fed 3M Forward”
A13: usd_brl | C13: Bloomberg | D13: USDBRL Curncy | E13: Explanatory variable: exchange rate between brazilian real (brl) and american dollar (usd) / USDBRL Spot Exchange Rate - Price of 1 USD in BRL
A14: gdp_yoy | C14: Bloomberg | D14: BZGDYOY% Index | E14: Explanatory variable: brazilian gdp growth / Real GDP (yoy %)
A15: sov_spread_5y | C15: Bloomberg | D15: BRAZIL CDS USD SR 5Y CBGN Curncy | E15: Explanatory variable: Brazilian CDS 5Y / 5 Year CDS | F15: a) el spread del gobierno de Brasil debería ser en REALES en un mismo maturity o tenor que el de cada bono corporate que seleccionaste , y que estén indexados por inflación los que correspondan. Usar el CDS 5Y es medir el riesgo de default de brasil en moneda USD y en mercados externos, thiago: o que devo fazer aqui: substituir o cds 5y(em usd) pela construcao de um spread do governo em reais? como seria isso? a curva DI menos a curva zero (ntnf + ltn) ? risco em dolar; substituir por risco em real? Como fazer isso?
A16: debt_gdp | C16: Bloomberg | D16: EHBBBR Index | E16: Explanatory variable: brazilian total debt to gdp / Budget Surplus/Deficit (% GDP) | F16: finalmente, "Debt to GDP" imagino es la deuda del gobierno? pero esta es deuda en cualquier moneda? externa también? Justifica: Sí, el indicador “Debt-to-GDP” se refiere a la deuda total del gobierno, y abarca tanto la deuda interna como la externa, independientemente de la moneda en que esté denominada. Esto significa que incluye: Bonos emitidos en reales (BRL) dentro del país, y Obligaciones en monedas extranjeras (como USD o EUR) frente a acreedores externos. Bloomberg recopila estos datos a partir de las estadísticas fiscales oficiales (por ejemplo, del Tesoro Nacional de Brasil o del FMI) y los expresa como porcentaje del PIB para facilitar comparaciones internacionales. En resumen, mide la deuda total del sector público general, en todas las monedas y frente a todo tipo de acreedor, convertida a moneda local para mantener coherencia. Características del pais: “Debt-to-GDP” se refiere a la deuda total del gobierno, y abarca tanto la deuda interna como la externa, independientemente de la moneda en que esté denominada. Esto significa que incluye: Bonos emitidos en reales (BRL) dentro del país, y Obligaciones en monedas extranjeras (como USD o EUR) frente a acreedores externos. Bloomberg recopila estos datos a partir de las estadísticas fiscales oficiales (por ejemplo, del Tesoro Nacional de Brasil o del FMI) y los expresa como porcentaje del PIB para facilitar comparaciones internacionales. En resumen, mide la deuda total del sector público general, en todas las monedas y frente a todo tipo de acreedor, convertida a moneda local para mantener coherencia.
A17: cf_cash_from_oper_to_ bs_tot_asset | C17: Bloomberg | D17: CF_CASH_FROM_OPER and BS_TOT_ASSET | E17: Explanatory variable: Operating cash flow relative to size (liquidity or profitability proxy) / Características de la empresa: liquidez | F17: b) las variables idiosincrásicas de las empresas deben ser ratios y no valores absolutos como Total Assets: podría ser Debt to Assets por ejemplo, o sobre Net Worth. thiago: ok, vou substituir
A18: amount_issued_to_bs_tot_asset | C18: Bloomberg | D18: AMOUNT ISSUED and BS_TOT_ASSET | E18: Explanatory variable: Financing intensity relative to balance sheet / Características del bono: monto emitido
A19: tot_debt_to_ebitda | C19: Bloomberg | D19: TOT_DEBT_TO_EBITDA | E19: Explanatory variable: Leverage measure / Características de la empresa: apalancamiento
A20: days_to_maturity | C20: Calculated | E20: Explanatory variable: days to maturity as per brazilian convention business days between observed date and maturity over 252 / Características del bono: madurez | F20: c) el time to maturity de cada bono debe ser una variable explicativa también y no está, thiago: ok, vou adicionar
A21: Synthetic_CDS_BRL | B21: Spread soberano en reales: dado que no existe un EMBI local soberano en reales publicado, se construirá un spread soberano en moneda local basado en bonos soberanos emitidos en Brasil en reales, emparejados por madurez y tipo de instrumento con los bonos corporativos. | C21: Calculated | D21: Spread soberano en reales: dado que no existe un EMBI local soberano en reales publicado, se construirá un spread soberano en moneda local basado en bonos soberanos emitidos en Brasil en reales, emparejados por madurez y tipo de instrumento con los bonos corporativos. | E21: En este trabajo se sustituyó el CDS soberano a cinco años en USD (que mide el riesgo de default de Brasil en mercados internacionales) por un “CDS sintético en reales” (CDS-BRL) construido íntegramente con datos domésticos. El indicador se obtuvo al comparar los rendimientos de los bonos soberanos LTN y NTN-F con la curva DI, y los de las NTN-B con la curva IPCA/WLA, generando una superficie de spreads soberanos en BRL mediante el modelo Nelson–Siegel. Posteriormente, se interpoló el valor de riesgo soberano correspondiente al mismo vencimiento de cada bono corporativo, permitiendo estimar el riesgo país en moneda local y aislar el riesgo de crédito corporativo puro dentro del mercado brasileño.
